Metadata-Version: 2.1
Name: GILBypass
Version: 0.1.0
Summary: GILBypass (GILB) is a module that allows you to bypass the Global Interpreter Lock (GIL) in Python.
Home-page: https://github.com/IHasBone/GILB
Author: IHasBone
Author-email: info@picstreme.com
License: MIT
Keywords: GIL,bypass,GILBypass,GILB,global interpreter lock
Classifier: Development Status :: 2 - Pre-Alpha
Classifier: Intended Audience :: Developers
Classifier: Operating System :: OS Independent
Classifier: License :: OSI Approved :: MIT License
Classifier: Programming Language :: Python :: 3
Requires-Python: >=3.10
License-File: LICENSE.txt
